Metadata-Version: 2.1
Name: pyscreenshotter
Version: 0.1.2
Summary: A simple screenshot application.
Home-page: UNKNOWN
Author: Garrett Jones
Author-email: jonesgc137@gmail.com
License: UNKNOWN
Keywords: opencv,keyboard,screenshot,pyautogui
Platform: UNKNOWN
Classifier: Programming Language :: Python :: 3
Classifier: Operating System :: Unix
Classifier: Operating System :: MacOS :: MacOS X
Classifier: Operating System :: Microsoft :: Windows
Requires-Python: >=3.0
License-File: LICENSE.md
